hilbertlens/__init__.py
hilbertlens/adapters.py
hilbertlens/core.py
hilbertlens/diagnose.py
hilbertlens/geometry.py
hilbertlens/spectral.py
hilbertlens/visualize.py
hilbertlens-0.1.3.dist-info/licenses/LICENSE
hilbertlens-0.1.3.dist-info/METADATA
hilbertlens-0.1.3.dist-info/WHEEL
hilbertlens-0.1.3.dist-info/top_level.txt
hilbertlens-0.1.3.dist-info/RECORD
