Metadata-Version: 2.4
Name: hilbertlens
Version: 0.1.3
Summary: A diagnostic suite for Quantum Machine Learning encodings.
Author-email: "Md. Abdullah Al Mamun" <abdullah18@temple.edu>
License: MIT License
Project-URL: Homepage, https://github.com/mamuncseru/hilbertlens
Classifier: Programming Language :: Python :: 3
Classifier: License :: OSI Approved :: MIT License
Classifier: Operating System :: OS Independent
Classifier: Topic :: Scientific/Engineering :: Physics
Classifier: Topic :: Scientific/Engineering :: Artificial Intelligence
Requires-Python: >=3.8
License-File: LICENSE
Requires-Dist: numpy>=1.20
Requires-Dist: matplotlib>=3.5
Requires-Dist: scikit-learn>=1.0
Requires-Dist: scipy>=1.7
Requires-Dist: qiskit>=1.0
Provides-Extra: pennylane
Requires-Dist: pennylane>=0.30; extra == "pennylane"
Provides-Extra: dev
Requires-Dist: pytest; extra == "dev"
Requires-Dist: black; extra == "dev"
Dynamic: license-file
